fish_speech/content_sequence.py
fish_speech/tokenizer.py
fish_speech/configs/base.yaml
fish_speech/configs/modded_dac_vq.yaml
fish_speech/configs/text2semantic_finetune.yaml
fish_speech/configs/lora/r_8_alpha_16.yaml
fish_speech/i18n/README.md
fish_speech/i18n/__init__.py
fish_speech/i18n/core.py
fish_speech/i18n/scan.py
fish_speech/i18n/locale/en_US.json
fish_speech/i18n/locale/es_ES.json
fish_speech/i18n/locale/ja_JP.json
fish_speech/i18n/locale/ko_KR.json
fish_speech/i18n/locale/pt_BR.json
fish_speech/i18n/locale/zh_CN.json
fish_speech/inference_engine/__init__.py
fish_speech/inference_engine/reference_loader.py
fish_speech/inference_engine/utils.py
fish_speech/inference_engine/vq_manager.py
fish_speech/models/dac/__init__.py
fish_speech/models/dac/inference.py
fish_speech/models/dac/modded_dac.py
fish_speech/models/dac/rvq.py
fish_speech/models/text2semantic/__init__.py
fish_speech/models/text2semantic/inference.py
fish_speech/models/text2semantic/llama.py
fish_speech/models/text2semantic/lora.py
fish_speech/text/__init__.py
fish_speech/text/clean.py
fish_speech/utils/__init__.py
fish_speech/utils/braceexpand.py
fish_speech/utils/context.py
fish_speech/utils/file.py
fish_speech/utils/instantiators.py
fish_speech/utils/logger.py
fish_speech/utils/logging_utils.py
fish_speech/utils/rich_utils.py
fish_speech/utils/schema.py
fish_speech/utils/spectrogram.py
fish_speech/utils/utils.py
fish_speech-0.1.0.dist-info/licenses/LICENSE
tools/api_client.py
tools/api_server.py
tools/download_models.py
tools/run_webui.py
tools/llama/quantize.py
tools/server/api_utils.py
tools/server/exception_handler.py
tools/server/inference.py
tools/server/model_manager.py
tools/server/model_utils.py
tools/server/views.py
tools/vqgan/create_train_split.py
tools/vqgan/extract_vq.py
tools/webui/__init__.py
tools/webui/inference.py
tools/webui/variables.py
fish_speech-0.1.0.dist-info/METADATA
fish_speech-0.1.0.dist-info/WHEEL
fish_speech-0.1.0.dist-info/top_level.txt
fish_speech-0.1.0.dist-info/RECORD
