Metadata-Version: 2.4
Name: fish-speech
Version: 0.1.0
Summary: Fish Speech
Author-email: Lengyue <lengyue@lengyue.me>
License: Apache-2.0
Keywords: TTS,Speech
Classifier: Programming Language :: Python :: 3
Requires-Python: >=3.10
License-File: LICENSE
Requires-Dist: numpy<=1.26.4
Requires-Dist: transformers>=4.45.2
Requires-Dist: datasets==2.18.0
Requires-Dist: lightning>=2.1.0
Requires-Dist: hydra-core>=1.3.2
Requires-Dist: tensorboard>=2.14.1
Requires-Dist: natsort>=8.4.0
Requires-Dist: einops>=0.7.0
Requires-Dist: librosa>=0.10.1
Requires-Dist: rich>=13.5.3
Requires-Dist: gradio>5.0.0
Requires-Dist: wandb>=0.15.11
Requires-Dist: grpcio>=1.58.0
Requires-Dist: kui>=1.6.0
Requires-Dist: uvicorn>=0.30.0
Requires-Dist: loguru>=0.6.0
Requires-Dist: loralib>=0.1.2
Requires-Dist: pyrootutils>=1.0.4
Requires-Dist: resampy>=0.4.3
Requires-Dist: einx[torch]==0.2.2
Requires-Dist: zstandard>=0.22.0
Requires-Dist: pydub
Requires-Dist: pyaudio
Requires-Dist: modelscope==1.17.1
Requires-Dist: opencc-python-reimplemented==0.1.7
Requires-Dist: silero-vad
Requires-Dist: ormsgpack
Requires-Dist: tiktoken>=0.8.0
Requires-Dist: pydantic==2.9.2
Requires-Dist: cachetools
Requires-Dist: descript-audio-codec
Requires-Dist: descript-audiotools
Provides-Extra: stable
Requires-Dist: torch>=2.5.1; extra == "stable"
Requires-Dist: torchaudio; extra == "stable"
Dynamic: license-file
